pytest_django_haystack.py
pytest_django_haystack-0.3.0.dist-info/DESCRIPTION.rst
pytest_django_haystack-0.3.0.dist-info/METADATA
pytest_django_haystack-0.3.0.dist-info/RECORD
pytest_django_haystack-0.3.0.dist-info/WHEEL
pytest_django_haystack-0.3.0.dist-info/entry_points.txt
pytest_django_haystack-0.3.0.dist-info/metadata.json
pytest_django_haystack-0.3.0.dist-info/top_level.txt
